gke_cache_builder/__init__.py
gke_cache_builder/cache_builder.py
gke_cache_builder/client_csv_handler.py
gke_cache_builder/nfs_cache_builder.py
gke_cache_builder/pyarmor_runtime_000000/__init__.py
gke_cache_builder-1.0.7.dist-info/licenses/LICENSE
gke_cache_builder-1.0.7.dist-info/METADATA
gke_cache_builder-1.0.7.dist-info/WHEEL
gke_cache_builder-1.0.7.dist-info/top_level.txt
gke_cache_builder-1.0.7.dist-info/RECORD
