Metadata-Version: 2.4
Name: gke-cache-builder
Version: 1.0.7
Summary: [Protected] GKE Multi-Cluster Cache Builder with Fuzzy Search
License: MIT
Project-URL: Homepage, https://github.com/yourusername/gke-cache-builder
Project-URL: Repository, https://github.com/yourusername/gke-cache-builder
Project-URL: Issues, https://github.com/yourusername/gke-cache-builder/issues
Keywords: gke,kubernetes,cache,fuzzy-search,multi-cluster
Classifier: Development Status :: 4 - Beta
Classifier: Intended Audience :: Developers
Classifier: License :: OSI Approved :: MIT License
Classifier: Programming Language :: Python :: 3
Classifier: Programming Language :: Python :: 3.8
Classifier: Programming Language :: Python :: 3.9
Classifier: Programming Language :: Python :: 3.10
Classifier: Programming Language :: Python :: 3.11
Requires-Python: >=3.8
License-File: LICENSE
Requires-Dist: google-cloud-resource-manager>=1.10.0
Requires-Dist: google-cloud-container>=2.30.0
Requires-Dist: google-auth>=2.23.0
Requires-Dist: kubernetes>=28.1.0
Requires-Dist: python-dotenv>=1.0.0
Dynamic: license-file
